{
  "state": "Massachusetts",
  "stateCode": "MA",
  "region": "na",
  "stance": "none",
  "stanceZoning": "none",
  "stanceAffordability": "none",
  "lastUpdated": "2026-04-16",
  "contextBlurb": "Massachusetts has no enacted AI or data-center law, but the legislature is considering a broad slate: emissions-reduction rules for AI and data centers, oversight of AI in healthcare decisions, codification of its facial-recognition commission recommendations, and general AI consumer protections.",
  "legislation": []
}